pirateplayer/__init__.py
pirateplayer/__main__.py
pirateplayer/controller.py
pirateplayer/library.py
pirateplayer/view.py
pirateplayer/assets/NotoSansMono-ExtraCondensedSemiBold.ttf
pirateplayer/assets/logo.png
pirateplayer/utils/__init__.py
pirateplayer/utils/confparse.py
pirateplayer/utils/gstreamer.py
pirateplayer/utils/inputmap.py
pirateplayer-0.3.3.dist-info/LICENSE
pirateplayer-0.3.3.dist-info/METADATA
pirateplayer-0.3.3.dist-info/WHEEL
pirateplayer-0.3.3.dist-info/entry_points.txt
pirateplayer-0.3.3.dist-info/top_level.txt
pirateplayer-0.3.3.dist-info/RECORD
