Metadata-Version: 2.1
Name: pirateplayer
Version: 0.3.3
Summary: PiratePlayer is an offline player for Pirate Audio
Home-page: https://github.com/TestDotCom/pirateplayer
Author: TestDotCom
License: MIT
Keywords: raspberry,rpi,pirate audio,gstreamer,player
Platform: UNKNOWN
Requires-Python: >=3.5
Requires-Dist: rpi.gpio
Requires-Dist: gpiozero
Requires-Dist: spidev
Requires-Dist: numpy
Requires-Dist: st7789
Requires-Dist: pillow
Requires-Dist: mutagen
Requires-Dist: pygobject
Requires-Dist: pykka
Provides-Extra: lint
Requires-Dist: autopep8 ; extra == 'lint'
Provides-Extra: release
Requires-Dist: twine ; extra == 'release'
Requires-Dist: wheel ; extra == 'release'
Provides-Extra: test
Requires-Dist: pytest-xdist ; extra == 'test'
Requires-Dist: pytest-cov ; extra == 'test'
